iddn/__init__.py
iddn/bcd.py
iddn/iddn.py
iddn/parameter_tuning_iddn.py
iddn/solver.py
iddn/tools.py
iddn/visualize_basic.py
iddn/visualize_multi.py
iddn_data/__init__.py
iddn_data/constraints.png
iddn_data/constraints_cartoon.png
iddn_data/constraints_fine.png
iddn_data/example.npz
iddn_data/iddn_overview.png
iddn_data/load_data.py
iddn_data/README.md
iddn_data/three_layers.png
iddn_data/two_part_network.npz
iddn_data/visualization_layout.png
tests/test_iddn.py
tests/test_iddn_constraints.py
iddn-0.2.4.dist-info/LICENSE
iddn-0.2.4.dist-info/METADATA
iddn-0.2.4.dist-info/WHEEL
iddn-0.2.4.dist-info/RECORD
