Metadata-Version: 2.1
Name: iddn
Version: 0.2.4
Summary: Multi-omics dependency network analysis under two conditions
License: MIT
Author: Yizhi Wang
Requires-Python: >=3.9
Classifier: License :: OSI Approved :: MIT License
Classifier: Programming Language :: Python :: 3
Classifier: Programming Language :: Python :: 3.9
Classifier: Programming Language :: Python :: 3.10
Classifier: Programming Language :: Python :: 3.11
Classifier: Programming Language :: Python :: 3.12
Requires-Dist: ddn3 (>=1.0.3)
Requires-Dist: jupyter (>=1.0.0)
Requires-Dist: matplotlib (>=3.8.2)
Requires-Dist: networkx (>=3.2.1)
Requires-Dist: numba (>=0.58.1)
Requires-Dist: numpy (>=1.26.2)
Requires-Dist: pandas (>=2.0.3)
Requires-Dist: scikit-learn (>=1.3.2)
Requires-Dist: scipy (>=1.11.4)
